README.rst
setup.py
ringcloud_pyapi/__init__.py
ringcloud_pyapi/ringcloud_pyapi.py
ringcloud_pyapi.egg-info/PKG-INFO
ringcloud_pyapi.egg-info/SOURCES.txt
ringcloud_pyapi.egg-info/dependency_links.txt
ringcloud_pyapi.egg-info/requires.txt
ringcloud_pyapi.egg-info/top_level.txt