Metadata-Version: 1.1
Name: ringcloud-pyapi
Version: 0.1.4
Summary: RingCloud API Client
Home-page: https://bitbucket.org/ringcloud/ringcloud_pyapi
Author: Mikhail Baranov
Author-email: devel@ringcloud.ru
License: MIT
Keywords: ringcloud,rest,api
Platform: UNKNOWN
Classifier: Intended Audience :: Developers
Classifier: Natural Language :: Russian
Classifier: License :: OSI Approved :: MIT License
Classifier: Operating System :: OS Independent
Classifier: Programming Language :: Python
Classifier: Programming Language :: Python :: 2
Classifier: Programming Language :: Python :: 2.7
Classifier: Programming Language :: Python :: 3
Classifier: Programming Language :: Python :: 3.3
Classifier: Topic :: Software Development :: Libraries :: Python Modules
